qdrouter_jinja2-0.1.10.dist-info/DESCRIPTION.rst
qdrouter_jinja2-0.1.10.dist-info/METADATA
qdrouter_jinja2-0.1.10.dist-info/RECORD
qdrouter_jinja2-0.1.10.dist-info/WHEEL
qdrouter_jinja2-0.1.10.dist-info/entry_points.txt
qdrouter_jinja2-0.1.10.dist-info/metadata.json
qdrouter_jinja2-0.1.10.dist-info/top_level.txt
qdrouterjinja2/Jinja2Writer.py
qdrouterjinja2/__init__.py
qdrouterjinja2/__main__.py
qdrouterjinja2/qdrouterjinja2.py
