Metadata-Version: 2.0
Name: qdrouter-jinja2
Version: 0.1.10
Summary: Generate qpid-dispatch config (qdrouter.conf) as Jinja2 template from already installed qpid-dispatch.
Home-page: https://github.com/rh-messaging-qe/qdrouterd-jinja2
Author: Dominik Lenoch <dlenoch@redhat.com>, Jakub Stejskal <jstejska@redhat.com>
Author-email: dlenoch@redhat.com
License: Apache 2.0
Platform: UNKNOWN
Requires-Dist: argparse
